llm_inception.py
llm_inception-0.2.1.dist-info/METADATA
llm_inception-0.2.1.dist-info/WHEEL
llm_inception-0.2.1.dist-info/entry_points.txt
llm_inception-0.2.1.dist-info/top_level.txt
llm_inception-0.2.1.dist-info/RECORD
