Metadata-Version: 2.4
Name: llm-inception
Version: 0.2.1
Summary: Run prompts against LLMs hosted by Inception Labs with diffusing animation
Author: NickMystic
Project-URL: Homepage, https://github.com/ghostofpokemon/llm-inception
Project-URL: Repository, https://github.com/ghostofpokemon/llm-inception
Project-URL: Changelog, https://github.com/ghostofpokemon/llm-inception/releases
Project-URL: Issues, https://github.com/ghostofpokemon/llm-inception/issues
Keywords: LLM,AI,Inception Labs,diffusing,plugin
Classifier: License :: OSI Approved :: MIT License
Requires-Python: >=3.9
Requires-Dist: llm>=0.22
Requires-Dist: httpx
Requires-Dist: httpx-sse
Requires-Dist: rich>=13.0
Provides-Extra: test
Requires-Dist: pytest; extra == "test"
Requires-Dist: pytest-httpx; extra == "test"
Requires-Dist: pytest-asyncio; extra == "test"
